apexxapi/__init__.py
apexxapi/client.py
apexxapi/utils.py
apexxapi-1.0.5.dist-info/LICENSE.MD
apexxapi-1.0.5.dist-info/METADATA
apexxapi-1.0.5.dist-info/WHEEL
apexxapi-1.0.5.dist-info/top_level.txt
apexxapi-1.0.5.dist-info/RECORD
