Metadata-Version: 2.1
Name: apexxapi
Version: 1.0.5
Summary: Package containing functions for accessing Apexx API 2.0
Home-page: https://github.com/HugoWickham/apexxpython
Author: Hugo Wickham
Author-email: hugo.wickham@apexx.global
License: UNKNOWN
Platform: UNKNOWN
Classifier: Programming Language :: Python :: 3
Classifier: License :: OSI Approved :: MIT License
Classifier: Operating System :: OS Independent
